parsecdi/__init__.py
parsecdi/parsecdi.py
parsecdi-0.0.2.dist-info/LICENSE
parsecdi-0.0.2.dist-info/METADATA
parsecdi-0.0.2.dist-info/WHEEL
parsecdi-0.0.2.dist-info/top_level.txt
parsecdi-0.0.2.dist-info/RECORD
